shape2geosparql/__init__.py
shape2geosparql/shape2geosparql.py
shape2geosparql/scripts/__init__.py
shape2geosparql/scripts/s2g_script.py
shape2geosparql-0.1.1.dist-info/LICENSE
shape2geosparql-0.1.1.dist-info/METADATA
shape2geosparql-0.1.1.dist-info/WHEEL
shape2geosparql-0.1.1.dist-info/entry_points.txt
shape2geosparql-0.1.1.dist-info/top_level.txt
shape2geosparql-0.1.1.dist-info/RECORD
