Metadata-Version: 2.1
Name: shape2geosparql
Version: 0.1.1
Summary: Convert shapefiles to GeoSPARQL
Home-page: https://github.com/nvitucci/shape2geosparql
Author: Nicola Vitucci
Author-email: nicola.vitucci@gmail.com
License: MIT
Platform: UNKNOWN
Classifier: Intended Audience :: Developers
Classifier: Intended Audience :: Science/Research
Classifier: License :: OSI Approved :: MIT License
Classifier: Programming Language :: Python :: 3
Classifier: Operating System :: OS Independent
Classifier: Topic :: Software Development :: Libraries
Classifier: Topic :: Software Development :: Libraries :: Python Modules
Requires-Python: >=3.0
Requires-Dist: rdflib
Requires-Dist: gdal
Requires-Dist: click
Provides-Extra: tests
Requires-Dist: pytest ; extra == 'tests'
